.gitattributes
.gitignore
LICENSE.md
MANIFEST.in
README.md
pytest.ini
setup.py
versionate.py
NAG_PyPOP.egg-info/PKG-INFO
NAG_PyPOP.egg-info/SOURCES.txt
NAG_PyPOP.egg-info/dependency_links.txt
NAG_PyPOP.egg-info/entry_points.txt
NAG_PyPOP.egg-info/requires.txt
NAG_PyPOP.egg-info/top_level.txt
NAG_PyPOP.egg-info/zip-safe
beamer/beamercolorthemepop.sty
beamer/beamerfontthemepop.sty
beamer/beamerinnerthemepop.sty
beamer/beamerouterthemepop.sty
beamer/beamerthemepop.sty
beamer/eu_logo.pdf
beamer/flag_yellow_eps.ps
beamer/pop_logo.eps
beamer/test.tex
bin/chop_and_analyze.sh
bin/chop_roi.sh
bin/extraempirun.sh
bin/ipynb_to_report
bin/modelfactors2precomputed.py
doc/Makefile
doc/source/api_hl.rst
doc/source/api_ll.rst
doc/source/conf.py
doc/source/doc.rst
doc/source/install.rst
doc/source/layout.rst
doc/source/quickstart.rst
doc/source/_static/css/kbd.css
ipython_templates/html_nocode.tpl
ipython_templates/pop_report.cls
ipython_templates/pop_report.tplx
ipython_templates/graphics/EU-logo.jpg
ipython_templates/graphics/pop-logo.png
presentations/launch_blog/launch_blog.md
pypop/__init__.py
pypop/_plotsettings.py
pypop/config.py
pypop/dimemas.py
pypop/examples.py
pypop/extrae.py
pypop/prv.py
pypop/server.py
pypop/traceset.py
pypop/version
pypop/version.py
pypop/backends/__init__.py
pypop/backends/extrae/__init__.py
pypop/backends/extrae/pcf.py
pypop/cfgs/clock_frequency.cfg
pypop/cfgs/dimemas_ideal.cfg
pypop/cfgs/dimemas_ideal.tmpconfig.cfg
pypop/cfgs/ideal.collectives
pypop/cfgs/omp_total_runtime.cfg
pypop/cfgs/omp_total_runtime_loop.cfg
pypop/cfgs/omp_total_runtime_task.cfg
pypop/cfgs/omp_useful_computation.cfg
pypop/cfgs/omp_useful_computation_loop.cfg
pypop/cfgs/omp_useful_computation_task.cfg
pypop/cfgs/serial_useful_computation.cfg
pypop/cfgs/serial_useful_computation_no_omp.cfg
pypop/cfgs/serial_useful_computation_omp_loop.cfg
pypop/cfgs/serial_useful_computation_omp_task.cfg
pypop/cfgs/total_res_stl_cycles.cfg
pypop/cfgs/total_runtime.cfg
pypop/cfgs/total_runtime_excl_disabled.cfg
pypop/cfgs/total_useful_computation.cfg
pypop/cfgs/useful_cycles.cfg
pypop/cfgs/useful_instructions.cfg
pypop/cli/__init__.py
pypop/cli/cli.py
pypop/cutters/single_region.skel
pypop/examples/AutoMetrics.ipynb
