Metadata-Version: 2.1
Name: NAG-PyPOP
Version: 0.3.4
Summary: Python notebook support for POP metrics and reports
Home-page: https://github.com/numericalalgorithmsgroup/pypop.git
Author: Numerical Algorithms Group
Author-email: phil.tooley@nag.co.uk
License: UNKNOWN
Platform: UNKNOWN
Classifier: Programming Language :: Python :: 3
Classifier: License :: OSI Approved :: BSD License
Classifier: Operating System :: OS Independent
Requires-Python: >=3.6
License-File: LICENSE.md
